ccontrol/__init__.py
ccontrol/ccontrol.py
ccontrol-0.0.1.dist-info/METADATA
ccontrol-0.0.1.dist-info/WHEEL
ccontrol-0.0.1.dist-info/top_level.txt
ccontrol-0.0.1.dist-info/RECORD
