Metadata-Version: 2.1
Name: ccontrol
Version: 0.0.1
Summary: library that simplifies working with the console
Home-page: https://github.com/INTERJL
Author: INTERJL
Author-email: makar.arapov.real@gmail.com
Project-URL: GitHub, https://github.com/INTERJL/ccontrol/tree/main?tab=MIT-1-ov-file
Keywords: console speed python
Classifier: Programming Language :: Python :: 3.11
Classifier: License :: OSI Approved :: MIT License
Classifier: Operating System :: OS Independent
Requires-Python: >=3.6
Requires-Dist: requests (>=2.25.1)
